odoo8_addon_product_standard_margin-8.0.2.0.0-py2.7-nspkg.pth
odoo_addons/product_standard_margin/__openerp__.py
odoo_addons/product_standard_margin/__init__.py
odoo_addons/product_standard_margin/README.rst
odoo_addons/product_standard_margin/models/product_product.py
odoo_addons/product_standard_margin/models/__init__.py
odoo_addons/product_standard_margin/i18n/product_standard_margin.pot
odoo_addons/product_standard_margin/i18n/nl.po
odoo_addons/product_standard_margin/i18n/fr.po
odoo_addons/product_standard_margin/views/view.xml
odoo_addons/product_standard_margin/data/decimal_precision.yml
odoo8_addon_product_standard_margin-8.0.2.0.0.dist-info/top_level.txt
odoo8_addon_product_standard_margin-8.0.2.0.0.dist-info/WHEEL
odoo8_addon_product_standard_margin-8.0.2.0.0.dist-info/RECORD
odoo8_addon_product_standard_margin-8.0.2.0.0.dist-info/metadata.json
odoo8_addon_product_standard_margin-8.0.2.0.0.dist-info/DESCRIPTION.rst
odoo8_addon_product_standard_margin-8.0.2.0.0.dist-info/METADATA
odoo8_addon_product_standard_margin-8.0.2.0.0.dist-info/namespace_packages.txt
